Aries/__init__.py
Aries/collections.py
Aries/command.py
Aries/db.py
Aries/docker.py
Aries/excel.py
Aries/files.py
Aries/oauth.py
Aries/outputs.py
Aries/strings.py
Aries/table.py
Aries/tasks.py
Aries/test.py
Aries/utils.py
Aries/web.py
Aries/Google/__init__.py
Aries/Google/drive.py
Aries/assets/file_signatures.json
Aries/assets/file_signatures_addon.json
Aries_core-0.1.330.dist-info/METADATA
Aries_core-0.1.330.dist-info/WHEEL
Aries_core-0.1.330.dist-info/top_level.txt
Aries_core-0.1.330.dist-info/RECORD
