Metadata-Version: 2.1
Name: Aries-core
Version: 0.1.330
Summary: Python package providing shortcuts to small tasks like string manipulation, running background tasks, configuring logging, accessing web API etc.
Home-page: https://github.com/qiuosier/Aries
Author: Qiu Qin
Author-email: qiuosier@gmail.com
License: UNKNOWN
Platform: UNKNOWN
Classifier: Programming Language :: Python :: 3
Classifier: License :: OSI Approved :: MIT License
Classifier: Operating System :: OS Independent
Requires-Python: >=3.6
Requires-Dist: openpyxl (==3.0.7)
Requires-Dist: requests (>=2.23.0)
Requires-Dist: lxml (>=4.5.1)
